pyeslogging/__init__.py
pyeslogging/handlers.py
pyeslogging/serializers.py
tests/__init__.py
tests/app.py
tests/test_pyeshandler.py
tests/test_pyesserializer.py
PYESHandler-1.0.2.dist-info/LICENSE.md
PYESHandler-1.0.2.dist-info/METADATA
PYESHandler-1.0.2.dist-info/WHEEL
PYESHandler-1.0.2.dist-info/top_level.txt
PYESHandler-1.0.2.dist-info/RECORD
