Metadata-Version: 2.1
Name: PYESHandler
Version: 1.0.2
Summary: Elasticsearch Log handler for the logging library
Home-page: https://github.com/mkhadher/python-elasticsearch-logger
Author: Mohammed Mousa
Author-email: m.khadher@hotmail.com
License: Apache2
Keywords: logging elasticsearch handler log django and flask instrumentation
Classifier: Development Status :: 5 - Production/Stable
Classifier: Intended Audience :: Developers
Classifier: Topic :: System :: Logging
Classifier: Topic :: Software Development :: Libraries
Classifier: Topic :: Internet :: Log Analysis
Classifier: License :: OSI Approved :: Apache Software License
Classifier: Programming Language :: Python :: 2.7
Classifier: Programming Language :: Python :: 3.8
License-File: LICENSE.md
Requires-Dist: elasticsearch
Requires-Dist: requests
Provides-Extra: dev
Requires-Dist: check-manifest ; extra == 'dev'
Requires-Dist: six ; extra == 'dev'
Requires-Dist: pylint ; extra == 'dev'
Provides-Extra: test
Requires-Dist: coverage ; extra == 'test'
